deployconfigs/__init__.py
deployconfigs/deployconfigs.py
deployconfigs/djangoconfigs.py
deployconfigs-1.3.4.dist-info/LICENSE
deployconfigs-1.3.4.dist-info/METADATA
deployconfigs-1.3.4.dist-info/WHEEL
deployconfigs-1.3.4.dist-info/top_level.txt
deployconfigs-1.3.4.dist-info/RECORD
