Metadata-Version: 2.1
Name: deployconfigs
Version: 1.3.4
Summary: A centralized place to handle deploy configs
Home-page: https://gitlab.com/tayyeb/deployconfigs
Author: wtayyeb
Author-email: wtayyeb@gmail.com
License: MIT
Classifier: Development Status :: 5 - Production/Stable
Classifier: Intended Audience :: Developers
Classifier: Topic :: Software Development :: Build Tools
Classifier: License :: OSI Approved :: MIT License
Classifier: Programming Language :: Python :: 3
Classifier: Programming Language :: Python :: 3.9
Classifier: Programming Language :: Python :: 3.10
Classifier: Programming Language :: Python :: 3.11
Classifier: Programming Language :: Python :: 3.12
License-File: LICENSE
